hypertune/data/aarch64/libhypertune.dylib
hypertune/data/aarch64/libhypertune.so
hypertune/data/hypertune.h
hypertune/data/x86_64/hypertune.dll
hypertune/data/x86_64/libhypertune.dylib
hypertune/data/x86_64/libhypertune.so
hypertune/lib/__init__.py
hypertune/lib/clib.py
hypertune/lib/node.py
hypertune/lib/py.typed
hypertune/py.typed
hypertune/sdk.py
hypertune_sdk-0.6.5.dist-info/METADATA
hypertune_sdk-0.6.5.dist-info/WHEEL
hypertune_sdk-0.6.5.dist-info/RECORD
